README.rst
setup.py
domain_director/__init__.py
domain_director/__main__.py
domain_director/blueprints.py
domain_director/cli.py
domain_director/domain.py
domain_director/location.py
domain_director/server.py
domain_director.egg-info/PKG-INFO
domain_director.egg-info/SOURCES.txt
domain_director.egg-info/dependency_links.txt
domain_director.egg-info/entry_points.txt
domain_director.egg-info/requires.txt
domain_director.egg-info/top_level.txt
domain_director/kml_converter/__init__.py
domain_director/kml_converter/__main__.py
domain_director/kml_converter/cli.py
domain_director/tests/__init__.py
domain_director/tests/test_domain.py
domain_director/tests/test_kml_converter.py
domain_director/tests/test_location.py
domain_director/tests/test_server.py
domain_director/tests/test_util.py