Metadata-Version: 1.0
Name: domain-director
Version: 0.0.2
Summary: Director-server for Freifunk mesh-nodes to acquire their mesh-domain
Home-page: https://www.github.com/blocktrron/domain-director
Author: David Bauer
Author-email: david@darmstadt.freifunk.net
License: AGPLv3
Platform: UNKNOWN
